{
  "1": {
    "class_type": "UNETLoader",
    "inputs": { "unet_name": "wan2.1_i2v_480p_14B_fp8_scaled.safetensors", "weight_dtype": "default" }
  },
  "19": {
    "class_type": "LoraLoaderModelOnly",
    "inputs": { "model": ["1", 0], "lora_name": "Wan21_T2V_14B_lightx2v_cfg_step_distill_lora_rank32.safetensors", "strength_model": 1.0 }
  },
  "2": {
    "class_type": "ModelSamplingSD3",
    "inputs": { "model": ["19", 0], "shift": 8.0 }
  },
  "3": {
    "class_type": "ModelPatchLoader",
    "inputs": { "name": "wan2.1_infiniteTalk_single_fp16.safetensors" }
  },
  "4": {
    "class_type": "VAELoader",
    "inputs": { "vae_name": "wan_2.1_vae.safetensors" }
  },
  "5": {
    "class_type": "CLIPLoader",
    "inputs": { "clip_name": "umt5_xxl_fp8_e4m3fn_scaled.safetensors", "type": "wan" }
  },
  "6": {
    "class_type": "CLIPTextEncode",
    "inputs": { "clip": ["5", 0], "text": "a woman talking expressively to camera, animated hand gestures, gesturing with hands while speaking, lively head movement, nodding, engaging body language, natural facial expressions, dynamic and energetic, soft studio lighting, high quality" }
  },
  "7": {
    "class_type": "CLIPTextEncode",
    "inputs": { "clip": ["5", 0], "text": "static, still, blurry, distorted face, deformed mouth, bad teeth, watermark, text, low quality" }
  },
  "8": {
    "class_type": "CLIPVisionLoader",
    "inputs": { "clip_name": "clip_vision_h.safetensors" }
  },
  "9": {
    "class_type": "LoadImage",
    "inputs": { "image": "avatar.png" }
  },
  "10": {
    "class_type": "CLIPVisionEncode",
    "inputs": { "clip_vision": ["8", 0], "image": ["9", 0], "crop": "center" }
  },
  "11": {
    "class_type": "AudioEncoderLoader",
    "inputs": { "audio_encoder_name": "wav2vec2-chinese-base_fp16.safetensors" }
  },
  "12": {
    "class_type": "LoadAudio",
    "inputs": { "audio": "speech.mp3" }
  },
  "13": {
    "class_type": "AudioEncoderEncode",
    "inputs": { "audio_encoder": ["11", 0], "audio": ["12", 0] }
  },
  "14": {
    "class_type": "WanInfiniteTalkToVideo",
    "inputs": {
      "mode": "single_speaker",
      "model": ["2", 0],
      "model_patch": ["3", 0],
      "positive": ["6", 0],
      "negative": ["7", 0],
      "vae": ["4", 0],
      "width": 480,
      "height": 832,
      "length": 81,
      "audio_encoder_output_1": ["13", 0],
      "motion_frame_count": 9,
      "audio_scale": 1.0,
      "clip_vision_output": ["10", 0],
      "start_image": ["9", 0]
    }
  },
  "15": {
    "class_type": "KSampler",
    "inputs": {
      "model": ["14", 0],
      "seed": 42,
      "steps": 4,
      "cfg": 1.0,
      "sampler_name": "euler",
      "scheduler": "simple",
      "positive": ["14", 1],
      "negative": ["14", 2],
      "latent_image": ["14", 3],
      "denoise": 1.0
    }
  },
  "16": {
    "class_type": "VAEDecode",
    "inputs": { "samples": ["15", 0], "vae": ["4", 0] }
  },
  "17": {
    "class_type": "CreateVideo",
    "inputs": { "images": ["16", 0], "fps": 25.0, "audio": ["12", 0], "bit_depth": 8 }
  },
  "18": {
    "class_type": "SaveVideo",
    "inputs": { "video": ["17", 0], "filename_prefix": "infinitetalk/talk", "format": "mp4", "codec": "h264" }
  }
}
